AUTHORS.rst
ChangeLog.rst
LICENSE
MANIFEST.in
README.rst
setup.py
gignore/__init__.py
gignore/cli.py
gignore/compat.py
gignore/utils.py
gignore.egg-info/PKG-INFO
gignore.egg-info/SOURCES.txt
gignore.egg-info/dependency_links.txt
gignore.egg-info/entry_points.txt
gignore.egg-info/top_level.txt